MANIFEST.in
README.rst
requirements-dev.txt
requirements.txt
setup.py
tox.ini
hungry/__init__.py
hungry.egg-info/PKG-INFO
hungry.egg-info/SOURCES.txt
hungry.egg-info/dependency_links.txt
hungry.egg-info/top_level.txt
test/test_eat.py