Metadata-Version: 1.1
Name: hungry
Version: 0.0.3
Summary: Easily eats exceptions using decorators
Home-page: https://github.com/denizdogan/hungry
Author: Deniz Dogan
Author-email: deniz@dogan.se
License: MIT
Platform: any
Classifier: Development Status :: 5 - Production/Stable
Classifier: Intended Audience :: Developers
Classifier: License :: OSI Approved :: MIT License
Classifier: Programming Language :: Python :: 2.7
Classifier: Topic :: Software Development :: Libraries :: Python Modules
Classifier: Operating System :: OS Independent
